lexicon/${name}_mod.v.lexicon_qs
lexicon/${name}_tb.v.lexicon_qs
lexicon/.gitignore
lexicon/__init__.py
lexicon/__main__.py
lexicon/author.py
lexicon/commonutils.py
lexicon/filegenerators.py
lexicon/main.py
lexicon/makegenerators.py
lexicon/module.py
lexicon/project.py
lexicon/subproject.py
lexicon_gauthamkrishna9991-0.1.2.dist-info/LICENSE
lexicon_gauthamkrishna9991-0.1.2.dist-info/METADATA
lexicon_gauthamkrishna9991-0.1.2.dist-info/WHEEL
lexicon_gauthamkrishna9991-0.1.2.dist-info/entry_points.txt
lexicon_gauthamkrishna9991-0.1.2.dist-info/RECORD
