Metadata-Version: 2.1
Name: lexicon-gauthamkrishna9991
Version: 0.1.2
Summary: A Verilog Project Management Tool
Author: Goutham Krishna K V
Author-email: gauthamkrishna9991@live.com
Requires-Python: >=3.9,<4.0
Classifier: License :: OSI Approved :: MIT License
Classifier: Operating System :: OS Independent
Classifier: Programming Language :: Python :: 3
Classifier: Programming Language :: Python :: 3.9
Classifier: Programming Language :: Python :: 3.10
Classifier: Programming Language :: Python :: 3.11
Classifier: Programming Language :: Python :: 3
Requires-Dist: PyYAML (==5.4.1)
Requires-Dist: blessed (>=1.19.1,<2.0.0)
Requires-Dist: colorama (==0.4.4)
Requires-Dist: inquirer (>=3.1.2,<4.0.0)
Requires-Dist: six (==1.15.0)
Requires-Dist: wcwidth (==0.2.5)
